AUTHORS.rst
CHANGES.rst
LICENSE.txt
MANIFEST.in
README.rst
setup.py
djfernet.egg-info/PKG-INFO
djfernet.egg-info/SOURCES.txt
djfernet.egg-info/dependency_links.txt
djfernet.egg-info/requires.txt
djfernet.egg-info/top_level.txt
fernet_fields/__init__.py
fernet_fields/fields.py
fernet_fields/hkdf.py
fernet_fields/utils.py