Metadata-Version: 2.1
Name: djfernet
Version: 0.8.0
Summary: UNKNOWN
Home-page: https://yourlabs.io/oss/djfernet
Author: James Pic
Author-email: jamespic@gmail.com
License: MIT
Keywords: fernet cryptography django
Platform: UNKNOWN
Requires-Python: >=3.8
